vdb37-0.5.0.dist-info/METADATA
vdb37-0.5.0.dist-info/WHEEL
vdb37/embeddings.py
vdb37/kv.py
vdb37/py.typed
vdb37/vdb37.pyi
vdb37/__init__.py
vdb37/vdb37.cp312-win_amd64.pyd
vdb37-0.5.0.dist-info/RECORD
