Metadata-Version: 2.3
Name: vdb37
Version: 0.5.0
Classifier: Programming Language :: Rust
Classifier: Programming Language :: Python :: Implementation :: CPython
Classifier: Programming Language :: Python :: Implementation :: PyPy
Summary: Simple vector database with Rust.
Keywords: vector,database,vdb,vector-database,rust
Author-email: AWeirdDev <aweirdscratcher@gmail.com>
Requires-Python: >=3.8
Project-URL: Homepage, https://github.com/AWeirdDev/vdb37
Project-URL: Bug Tracker, https://github.com/AWeirdDev/vdb37/issues
